<?xml version="1.0" encoding="UTF-8"?>
<analysisEngineDescription xmlns="http://uima.apache.org/resourceSpecifier">
    <frameworkImplementation>org.apache.uima.java</frameworkImplementation>
    <primitive>true</primitive>
    <annotatorImplementationName>org.apache.uima.ruta.engine.RutaEngine</annotatorImplementationName>
    <analysisEngineMetaData>
        <name>BasicEngine</name>
        <description/>
        <version>1.0</version>
        <vendor/>
        <configurationParameters searchStrategy="language_fallback">
            <configurationParameter>
                <name>seeders</name>
                <type>String</type>
                <multiValued>true</multiValued>
                <mandatory>false</mandatory>
            </configurationParameter>
            <configurationParameter>
                <name>debug</name>
                <type>Boolean</type>
                <multiValued>false</multiValued>
                <mandatory>false</mandatory>
            </configurationParameter>
            <configurationParameter>
                <name>additionalScripts</name>
                <type>String</type>
                <multiValued>true</multiValued>
                <mandatory>false</mandatory>
            </configurationParameter>
            <configurationParameter>
                <name>profile</name>
                <type>Boolean</type>
                <multiValued>false</multiValued>
                <mandatory>false</mandatory>
            </configurationParameter>
            <configurationParameter>
                <name>debugWithMatches</name>
                <type>Boolean</type>
                <multiValued>false</multiValued>
                <mandatory>false</mandatory>
            </configurationParameter>
            <configurationParameter>
                <name>statistics</name>
                <type>Boolean</type>
                <multiValued>false</multiValued>
                <mandatory>false</mandatory>
            </configurationParameter>
            <configurationParameter>
                <name>additionalEngines</name>
                <type>String</type>
                <multiValued>true</multiValued>
                <mandatory>false</mandatory>
            </configurationParameter>
            <configurationParameter>
                <name>additionalExtensions</name>
                <type>String</type>
                <multiValued>true</multiValued>
                <mandatory>false</mandatory>
            </configurationParameter>
            <configurationParameter>
                <name>debugOnlyFor</name>
                <type>String</type>
                <multiValued>true</multiValued>
                <mandatory>false</mandatory>
            </configurationParameter>
            <configurationParameter>
                <name>scriptEncoding</name>
                <type>String</type>
                <multiValued>false</multiValued>
                <mandatory>false</mandatory>
            </configurationParameter>
            <configurationParameter>
                <name>additionalEngineLoaders</name>
                <type>String</type>
                <multiValued>true</multiValued>
                <mandatory>false</mandatory>
            </configurationParameter>
            <configurationParameter>
                <name>resourcePaths</name>
                <type>String</type>
                <multiValued>true</multiValued>
                <mandatory>false</mandatory>
            </configurationParameter>
            <configurationParameter>
                <name>defaultFilteredTypes</name>
                <type>String</type>
                <multiValued>true</multiValued>
                <mandatory>false</mandatory>
            </configurationParameter>
            <configurationParameter>
                <name>mainScript</name>
                <type>String</type>
                <multiValued>false</multiValued>
                <mandatory>false</mandatory>
            </configurationParameter>
            <configurationParameter>
                <name>scriptPaths</name>
                <type>String</type>
                <multiValued>true</multiValued>
                <mandatory>false</mandatory>
            </configurationParameter>
            <configurationParameter>
                <name>descriptorPaths</name>
                <type>String</type>
                <multiValued>true</multiValued>
                <mandatory>false</mandatory>
            </configurationParameter>
            <configurationParameter>
                <name>removeBasics</name>
                <type>Boolean</type>
                <multiValued>false</multiValued>
                <mandatory>false</mandatory>
            </configurationParameter>
            <configurationParameter>
                <name>dynamicAnchoring</name>
                <description>Activates dynamic anchoring (possible speed up).</description>
                <type>Boolean</type>
                <multiValued>false</multiValued>
                <mandatory>false</mandatory>
            </configurationParameter>
            <configurationParameter>
                <name>greedyRuleElement</name>
                <description>Activates greedy anchoring for rule elements.</description>
                <type>Boolean</type>
                <multiValued>false</multiValued>
                <mandatory>false</mandatory>
            </configurationParameter>
            <configurationParameter>
                <name>greedyRule</name>
                <description>Activates greedy anchoring for complete rules.</description>
                <type>Boolean</type>
                <multiValued>false</multiValued>
                <mandatory>false</mandatory>
            </configurationParameter>
            <configurationParameter>
                <name>lowMemoryProfile</name>
                <type>Boolean</type>
                <multiValued>false</multiValued>
                <mandatory>false</mandatory>
            </configurationParameter>
            <configurationParameter>
                <name>createdBy</name>
                <type>Boolean</type>
                <multiValued>false</multiValued>
                <mandatory>false</mandatory>
            </configurationParameter>
            <configurationParameter>
                <name>simpleGreedyForComposed</name>
                <type>Boolean</type>
                <multiValued>false</multiValued>
                <mandatory>false</mandatory>
            </configurationParameter>
            <configurationParameter>
                <name>additionalUimafitEngines</name>
                <type>String</type>
                <multiValued>true</multiValued>
                <mandatory>false</mandatory>
            </configurationParameter>
            <configurationParameter>
                <name>strictImports</name>
                <type>Boolean</type>
                <multiValued>false</multiValued>
                <mandatory>false</mandatory>
            </configurationParameter>
        </configurationParameters>
        <configurationParameterSettings>
            <nameValuePair>
                <name>debug</name>
                <value>
                    <boolean>false</boolean>
                </value>
            </nameValuePair>
            <nameValuePair>
                <name>profile</name>
                <value>
                    <boolean>false</boolean>
                </value>
            </nameValuePair>
            <nameValuePair>
                <name>debugWithMatches</name>
                <value>
                    <boolean>true</boolean>
                </value>
            </nameValuePair>
            <nameValuePair>
                <name>defaultFilteredTypes</name>
                <value>
                    <array>
                        <string>org.apache.uima.ruta.type.SPACE</string>
                        <string>org.apache.uima.ruta.type.NBSP</string>
                        <string>org.apache.uima.ruta.type.BREAK</string>
                        <string>org.apache.uima.ruta.type.MARKUP</string>
                    </array>
                </value>
            </nameValuePair>
            <nameValuePair>
                <name>removeBasics</name>
                <value>
                    <boolean>false</boolean>
                </value>
            </nameValuePair>
            <nameValuePair>
                <name>seeders</name>
                <value>
                    <array>
                        <string>org.apache.uima.ruta.seed.DefaultSeeder</string>
                    </array>
                </value>
            </nameValuePair>
            <nameValuePair>
                <name>createdBy</name>
                <value>
                    <boolean>false</boolean>
                </value>
            </nameValuePair>
            <nameValuePair>
                <name>mainScript</name>
                <value>
                    <string>Main</string>
                </value>
            </nameValuePair>
            <nameValuePair>
                <name>scriptPaths</name>
                <value>
                    <array>
                        <string>/home/vinicius.matos/LabXP/cogroo4/cogroo-ruta/script</string>
                    </array>
                </value>
            </nameValuePair>
            <nameValuePair>
                <name>descriptorPaths</name>
                <value>
                    <array>
                        <string>/home/vinicius.matos/LabXP/cogroo4/cogroo-ruta/descriptor</string>
                    </array>
                </value>
            </nameValuePair>
            <nameValuePair>
                <name>resourcePaths</name>
                <value>
                    <array>
                        <string>/home/vinicius.matos/LabXP/cogroo4/cogroo-ruta/resources</string>
                    </array>
                </value>
            </nameValuePair>
            <nameValuePair>
                <name>additionalScripts</name>
                <value>
                    <array/>
                </value>
            </nameValuePair>
            <nameValuePair>
                <name>additionalEngines</name>
                <value>
                    <array/>
                </value>
            </nameValuePair>
            <nameValuePair>
                <name>additionalUimafitEngines</name>
                <value>
                    <array/>
                </value>
            </nameValuePair>
            <nameValuePair>
                <name>additionalExtensions</name>
                <value>
                    <array/>
                </value>
            </nameValuePair>
            <nameValuePair>
                <name>additionalEngineLoaders</name>
                <value>
                    <array/>
                </value>
            </nameValuePair>
        </configurationParameterSettings>
        <typeSystemDescription>
            <name>MainTypeSystem</name>
            <imports>
                <import location="BasicTypeSystem.xml"/>
                <import location="TypeSystem.xml"/>
            </imports>
            <types>
                <typeDescription>
                    <name>cogroo.ruta.Main.ADJECTIVE</name>
                    <description>Type defined in cogroo.ruta.Main</description>
                    <supertypeName>uima.tcas.Annotation</supertypeName>
                </typeDescription>
                <typeDescription>
                    <name>cogroo.ruta.Main.ADVERB</name>
                    <description>Type defined in cogroo.ruta.Main</description>
                    <supertypeName>uima.tcas.Annotation</supertypeName>
                </typeDescription>
                <typeDescription>
                    <name>cogroo.ruta.Main.ARTICLE</name>
                    <description>Type defined in cogroo.ruta.Main</description>
                    <supertypeName>uima.tcas.Annotation</supertypeName>
                </typeDescription>
                <typeDescription>
                    <name>cogroo.ruta.Main.DEFINITE</name>
                    <description>Type defined in cogroo.ruta.Main</description>
                    <supertypeName>uima.tcas.Annotation</supertypeName>
                </typeDescription>
                <typeDescription>
                    <name>cogroo.ruta.Main.INDEFINITE</name>
                    <description>Type defined in cogroo.ruta.Main</description>
                    <supertypeName>uima.tcas.Annotation</supertypeName>
                </typeDescription>
                <typeDescription>
                    <name>cogroo.ruta.Main.CONJUNCTION</name>
                    <description>Type defined in cogroo.ruta.Main</description>
                    <supertypeName>uima.tcas.Annotation</supertypeName>
                </typeDescription>
                <typeDescription>
                    <name>cogroo.ruta.Main.SUBORDINATING_CONJUNCTION</name>
                    <description>Type defined in cogroo.ruta.Main</description>
                    <supertypeName>uima.tcas.Annotation</supertypeName>
                </typeDescription>
                <typeDescription>
                    <name>cogroo.ruta.Main.COORDINATING_CONJUNCTION</name>
                    <description>Type defined in cogroo.ruta.Main</description>
                    <supertypeName>uima.tcas.Annotation</supertypeName>
                </typeDescription>
                <typeDescription>
                    <name>cogroo.ruta.Main.INTERJECTION</name>
                    <description>Type defined in cogroo.ruta.Main</description>
                    <supertypeName>uima.tcas.Annotation</supertypeName>
                </typeDescription>
                <typeDescription>
                    <name>cogroo.ruta.Main.NOUN</name>
                    <description>Type defined in cogroo.ruta.Main</description>
                    <supertypeName>uima.tcas.Annotation</supertypeName>
                </typeDescription>
                <typeDescription>
                    <name>cogroo.ruta.Main.PROPER_NOUN</name>
                    <description>Type defined in cogroo.ruta.Main</description>
                    <supertypeName>uima.tcas.Annotation</supertypeName>
                </typeDescription>
                <typeDescription>
                    <name>cogroo.ruta.Main.NUMERAL</name>
                    <description>Type defined in cogroo.ruta.Main</description>
                    <supertypeName>uima.tcas.Annotation</supertypeName>
                </typeDescription>
                <typeDescription>
                    <name>cogroo.ruta.Main.PREPOSITION</name>
                    <description>Type defined in cogroo.ruta.Main</description>
                    <supertypeName>uima.tcas.Annotation</supertypeName>
                </typeDescription>
                <typeDescription>
                    <name>cogroo.ruta.Main.PRONOUN</name>
                    <description>Type defined in cogroo.ruta.Main</description>
                    <supertypeName>uima.tcas.Annotation</supertypeName>
                </typeDescription>
                <typeDescription>
                    <name>cogroo.ruta.Main.PERSONAL_PRONOUN</name>
                    <description>Type defined in cogroo.ruta.Main</description>
                    <supertypeName>uima.tcas.Annotation</supertypeName>
                </typeDescription>
                <typeDescription>
                    <name>cogroo.ruta.Main.DETERMINATIVE_PRONOUN</name>
                    <description>Type defined in cogroo.ruta.Main</description>
                    <supertypeName>uima.tcas.Annotation</supertypeName>
                </typeDescription>
                <typeDescription>
                    <name>cogroo.ruta.Main.INDEPENDENT_PRONOUN</name>
                    <description>Type defined in cogroo.ruta.Main</description>
                    <supertypeName>uima.tcas.Annotation</supertypeName>
                </typeDescription>
                <typeDescription>
                    <name>cogroo.ruta.Main.VERB</name>
                    <description>Type defined in cogroo.ruta.Main</description>
                    <supertypeName>uima.tcas.Annotation</supertypeName>
                </typeDescription>
                <typeDescription>
                    <name>cogroo.ruta.Main.FINITE_VERB</name>
                    <description>Type defined in cogroo.ruta.Main</description>
                    <supertypeName>uima.tcas.Annotation</supertypeName>
                </typeDescription>
                <typeDescription>
                    <name>cogroo.ruta.Main.INFINITE_VERB</name>
                    <description>Type defined in cogroo.ruta.Main</description>
                    <supertypeName>uima.tcas.Annotation</supertypeName>
                </typeDescription>
                <typeDescription>
                    <name>cogroo.ruta.Main.PARTICIPLE_VERB</name>
                    <description>Type defined in cogroo.ruta.Main</description>
                    <supertypeName>uima.tcas.Annotation</supertypeName>
                </typeDescription>
                <typeDescription>
                    <name>cogroo.ruta.Main.GERUND_VERB</name>
                    <description>Type defined in cogroo.ruta.Main</description>
                    <supertypeName>uima.tcas.Annotation</supertypeName>
                </typeDescription>
                <typeDescription>
                    <name>cogroo.ruta.Main.PRESENT</name>
                    <description>Type defined in cogroo.ruta.Main</description>
                    <supertypeName>uima.tcas.Annotation</supertypeName>
                </typeDescription>
                <typeDescription>
                    <name>cogroo.ruta.Main.IMPERFECT</name>
                    <description>Type defined in cogroo.ruta.Main</description>
                    <supertypeName>uima.tcas.Annotation</supertypeName>
                </typeDescription>
                <typeDescription>
                    <name>cogroo.ruta.Main.SIMPLE_PERFECT</name>
                    <description>Type defined in cogroo.ruta.Main</description>
                    <supertypeName>uima.tcas.Annotation</supertypeName>
                </typeDescription>
                <typeDescription>
                    <name>cogroo.ruta.Main.PLU_PERFECT</name>
                    <description>Type defined in cogroo.ruta.Main</description>
                    <supertypeName>uima.tcas.Annotation</supertypeName>
                </typeDescription>
                <typeDescription>
                    <name>cogroo.ruta.Main.FUTURE</name>
                    <description>Type defined in cogroo.ruta.Main</description>
                    <supertypeName>uima.tcas.Annotation</supertypeName>
                </typeDescription>
                <typeDescription>
                    <name>cogroo.ruta.Main.CONDITIONAL</name>
                    <description>Type defined in cogroo.ruta.Main</description>
                    <supertypeName>uima.tcas.Annotation</supertypeName>
                </typeDescription>
                <typeDescription>
                    <name>cogroo.ruta.Main.INDICATIVE</name>
                    <description>Type defined in cogroo.ruta.Main</description>
                    <supertypeName>uima.tcas.Annotation</supertypeName>
                </typeDescription>
                <typeDescription>
                    <name>cogroo.ruta.Main.SUBJUNCTIVE</name>
                    <description>Type defined in cogroo.ruta.Main</description>
                    <supertypeName>uima.tcas.Annotation</supertypeName>
                </typeDescription>
                <typeDescription>
                    <name>cogroo.ruta.Main.IMPERATIVE</name>
                    <description>Type defined in cogroo.ruta.Main</description>
                    <supertypeName>uima.tcas.Annotation</supertypeName>
                </typeDescription>
                <typeDescription>
                    <name>cogroo.ruta.Main.MALE</name>
                    <description>Type defined in cogroo.ruta.Main</description>
                    <supertypeName>uima.tcas.Annotation</supertypeName>
                </typeDescription>
                <typeDescription>
                    <name>cogroo.ruta.Main.FEMALE</name>
                    <description>Type defined in cogroo.ruta.Main</description>
                    <supertypeName>uima.tcas.Annotation</supertypeName>
                </typeDescription>
                <typeDescription>
                    <name>cogroo.ruta.Main.SINGULAR</name>
                    <description>Type defined in cogroo.ruta.Main</description>
                    <supertypeName>uima.tcas.Annotation</supertypeName>
                </typeDescription>
                <typeDescription>
                    <name>cogroo.ruta.Main.PLURAL</name>
                    <description>Type defined in cogroo.ruta.Main</description>
                    <supertypeName>uima.tcas.Annotation</supertypeName>
                </typeDescription>
                <typeDescription>
                    <name>cogroo.ruta.Main.FIRST_PERSON</name>
                    <description>Type defined in cogroo.ruta.Main</description>
                    <supertypeName>uima.tcas.Annotation</supertypeName>
                </typeDescription>
                <typeDescription>
                    <name>cogroo.ruta.Main.SECOND_PERSON</name>
                    <description>Type defined in cogroo.ruta.Main</description>
                    <supertypeName>uima.tcas.Annotation</supertypeName>
                </typeDescription>
                <typeDescription>
                    <name>cogroo.ruta.Main.THIRD_PERSON</name>
                    <description>Type defined in cogroo.ruta.Main</description>
                    <supertypeName>uima.tcas.Annotation</supertypeName>
                </typeDescription>
                <typeDescription>
                    <name>cogroo.ruta.Main.FEMALE_NOUN</name>
                    <description>Type defined in cogroo.ruta.Main</description>
                    <supertypeName>uima.tcas.Annotation</supertypeName>
                </typeDescription>
                <typeDescription>
                    <name>cogroo.ruta.Main.MALE_NOUN</name>
                    <description>Type defined in cogroo.ruta.Main</description>
                    <supertypeName>uima.tcas.Annotation</supertypeName>
                </typeDescription>
                <typeDescription>
                    <name>cogroo.ruta.Main.PLURAL_NOUN</name>
                    <description>Type defined in cogroo.ruta.Main</description>
                    <supertypeName>uima.tcas.Annotation</supertypeName>
                </typeDescription>
                <typeDescription>
                    <name>cogroo.ruta.Main.SINGULAR_NOUN</name>
                    <description>Type defined in cogroo.ruta.Main</description>
                    <supertypeName>uima.tcas.Annotation</supertypeName>
                </typeDescription>
                <typeDescription>
                    <name>cogroo.ruta.Main.PROBLEM</name>
                    <description>Type defined in cogroo.ruta.Main</description>
                    <supertypeName>uima.tcas.Annotation</supertypeName>
                </typeDescription>
                <typeDescription>
                    <name>cogroo.ruta.Main.PROBLEM_INFO</name>
                    <description>Type defined in cogroo.ruta.Main</description>
                    <supertypeName>uima.tcas.Annotation</supertypeName>
                    <features>
                        <featureDescription>
                            <name>description</name>
                            <description>description</description>
                            <rangeTypeName>uima.cas.String</rangeTypeName>
                        </featureDescription>
                        <featureDescription>
                            <name>suggestion</name>
                            <description>suggestion</description>
                            <rangeTypeName>uima.cas.String</rangeTypeName>
                        </featureDescription>
                    </features>
                </typeDescription>
                <typeDescription>
                    <name>cogroo.ruta.Main.SUGGESTION</name>
                    <description>Type defined in cogroo.ruta.Main</description>
                    <supertypeName>uima.tcas.Annotation</supertypeName>
                    <features>
                        <featureDescription>
                            <name>text</name>
                            <description>text</description>
                            <rangeTypeName>uima.cas.String</rangeTypeName>
                        </featureDescription>
                    </features>
                </typeDescription>
                <typeDescription>
                    <name>cogroo.ruta.Main.END_PRONOUN</name>
                    <description>Type defined in cogroo.ruta.Main</description>
                    <supertypeName>uima.tcas.Annotation</supertypeName>
                </typeDescription>
                <typeDescription>
                    <name>cogroo.ruta.Main.END_NOS</name>
                    <description>Type defined in cogroo.ruta.Main</description>
                    <supertypeName>uima.tcas.Annotation</supertypeName>
                </typeDescription>
                <typeDescription>
                    <name>cogroo.ruta.Main.FEMALE_ADJECTIVE</name>
                    <description>Type defined in cogroo.ruta.Main</description>
                    <supertypeName>uima.tcas.Annotation</supertypeName>
                </typeDescription>
                <typeDescription>
                    <name>cogroo.ruta.Main.MALE_ADJECTIVE</name>
                    <description>Type defined in cogroo.ruta.Main</description>
                    <supertypeName>uima.tcas.Annotation</supertypeName>
                </typeDescription>
                <typeDescription>
                    <name>cogroo.ruta.Main.PLURAL_ADJECTIVE</name>
                    <description>Type defined in cogroo.ruta.Main</description>
                    <supertypeName>uima.tcas.Annotation</supertypeName>
                </typeDescription>
                <typeDescription>
                    <name>cogroo.ruta.Main.SINGULAR_ADJECTIVE</name>
                    <description>Type defined in cogroo.ruta.Main</description>
                    <supertypeName>uima.tcas.Annotation</supertypeName>
                </typeDescription>
                <typeDescription>
                    <name>cogroo.ruta.Main.LEXEME_A</name>
                    <description>Type defined in cogroo.ruta.Main</description>
                    <supertypeName>uima.tcas.Annotation</supertypeName>
                </typeDescription>
                <typeDescription>
                    <name>cogroo.ruta.Main.LEXEME_AS</name>
                    <description>Type defined in cogroo.ruta.Main</description>
                    <supertypeName>uima.tcas.Annotation</supertypeName>
                </typeDescription>
                <typeDescription>
                    <name>cogroo.ruta.Main.LEXEME_A_OR_AS</name>
                    <description>Type defined in cogroo.ruta.Main</description>
                    <supertypeName>uima.tcas.Annotation</supertypeName>
                </typeDescription>
                <typeDescription>
                    <name>cogroo.ruta.Main.PREPOSITION_A</name>
                    <description>Type defined in cogroo.ruta.Main</description>
                    <supertypeName>uima.tcas.Annotation</supertypeName>
                </typeDescription>
                <typeDescription>
                    <name>cogroo.ruta.Main.ARTICLE_A</name>
                    <description>Type defined in cogroo.ruta.Main</description>
                    <supertypeName>uima.tcas.Annotation</supertypeName>
                </typeDescription>
                <typeDescription>
                    <name>cogroo.ruta.Main.CRASE</name>
                    <description>Type defined in cogroo.ruta.Main</description>
                    <supertypeName>uima.tcas.Annotation</supertypeName>
                </typeDescription>
                <typeDescription>
                    <name>cogroo.ruta.Main.CRASE_A</name>
                    <description>Type defined in cogroo.ruta.Main</description>
                    <supertypeName>uima.tcas.Annotation</supertypeName>
                </typeDescription>
                <typeDescription>
                    <name>cogroo.ruta.Main.CRASE_AS</name>
                    <description>Type defined in cogroo.ruta.Main</description>
                    <supertypeName>uima.tcas.Annotation</supertypeName>
                </typeDescription>
                <typeDescription>
                    <name>cogroo.ruta.Main.PRON_TRATAMENTO</name>
                    <description>Type defined in cogroo.ruta.Main</description>
                    <supertypeName>uima.tcas.Annotation</supertypeName>
                </typeDescription>
                <typeDescription>
                    <name>cogroo.ruta.Main.EM_RELACAO</name>
                    <description>Type defined in cogroo.ruta.Main</description>
                    <supertypeName>uima.tcas.Annotation</supertypeName>
                </typeDescription>
                <typeDescription>
                    <name>cogroo.ruta.Main.COM_RELACAO</name>
                    <description>Type defined in cogroo.ruta.Main</description>
                    <supertypeName>uima.tcas.Annotation</supertypeName>
                </typeDescription>
                <typeDescription>
                    <name>cogroo.ruta.Main.FAZER_TEMPO</name>
                    <description>Type defined in cogroo.ruta.Main</description>
                    <supertypeName>uima.tcas.Annotation</supertypeName>
                </typeDescription>
                <typeDescription>
                    <name>cogroo.ruta.Main.EXP_TEMPO_S</name>
                    <description>Type defined in cogroo.ruta.Main</description>
                    <supertypeName>uima.tcas.Annotation</supertypeName>
                </typeDescription>
                <typeDescription>
                    <name>cogroo.ruta.Main.EXP_TEMPO_P</name>
                    <description>Type defined in cogroo.ruta.Main</description>
                    <supertypeName>uima.tcas.Annotation</supertypeName>
                </typeDescription>
                <typeDescription>
                    <name>cogroo.ruta.Main.VERB_LIST</name>
                    <description>Type defined in cogroo.ruta.Main</description>
                    <supertypeName>uima.tcas.Annotation</supertypeName>
                </typeDescription>
                <typeDescription>
                    <name>cogroo.ruta.Main.SE_OU_QUANDO</name>
                    <description>Type defined in cogroo.ruta.Main</description>
                    <supertypeName>uima.tcas.Annotation</supertypeName>
                </typeDescription>
                <typeDescription>
                    <name>cogroo.ruta.Main.EU_OU_ELE</name>
                    <description>Type defined in cogroo.ruta.Main</description>
                    <supertypeName>uima.tcas.Annotation</supertypeName>
                </typeDescription>
                <typeDescription>
                    <name>cogroo.ruta.Main.VERB_IRREG_75_77</name>
                    <description>Type defined in cogroo.ruta.Main</description>
                    <supertypeName>uima.tcas.Annotation</supertypeName>
                </typeDescription>
                <typeDescription>
                    <name>cogroo.ruta.Main.MAL</name>
                    <description>Type defined in cogroo.ruta.Main</description>
                    <supertypeName>uima.tcas.Annotation</supertypeName>
                </typeDescription>
                <typeDescription>
                    <name>cogroo.ruta.Main.MAU</name>
                    <description>Type defined in cogroo.ruta.Main</description>
                    <supertypeName>uima.tcas.Annotation</supertypeName>
                </typeDescription>
                <typeDescription>
                    <name>cogroo.ruta.Main.MEIA_SUB</name>
                    <description>Type defined in cogroo.ruta.Main</description>
                    <supertypeName>uima.tcas.Annotation</supertypeName>
                </typeDescription>
                <typeDescription>
                    <name>cogroo.ruta.Main.MEIA_NUM</name>
                    <description>Type defined in cogroo.ruta.Main</description>
                    <supertypeName>uima.tcas.Annotation</supertypeName>
                </typeDescription>
                <typeDescription>
                    <name>cogroo.ruta.Main.LEXEME_DE</name>
                    <description>Type defined in cogroo.ruta.Main</description>
                    <supertypeName>uima.tcas.Annotation</supertypeName>
                </typeDescription>
                <typeDescription>
                    <name>cogroo.ruta.Main.LEXEME_O</name>
                    <description>Type defined in cogroo.ruta.Main</description>
                    <supertypeName>uima.tcas.Annotation</supertypeName>
                </typeDescription>
                <typeDescription>
                    <name>cogroo.ruta.Main.LEXEME_DO</name>
                    <description>Type defined in cogroo.ruta.Main</description>
                    <supertypeName>uima.tcas.Annotation</supertypeName>
                </typeDescription>
                <typeDescription>
                    <name>cogroo.ruta.Main.ADJECTIVE</name>
                    <description>Type defined in cogroo.ruta.Main</description>
                    <supertypeName>uima.tcas.Annotation</supertypeName>
                </typeDescription>
                <typeDescription>
                    <name>cogroo.ruta.Main.ADVERB</name>
                    <description>Type defined in cogroo.ruta.Main</description>
                    <supertypeName>uima.tcas.Annotation</supertypeName>
                </typeDescription>
                <typeDescription>
                    <name>cogroo.ruta.Main.ARTICLE</name>
                    <description>Type defined in cogroo.ruta.Main</description>
                    <supertypeName>uima.tcas.Annotation</supertypeName>
                </typeDescription>
                <typeDescription>
                    <name>cogroo.ruta.Main.DEFINITE</name>
                    <description>Type defined in cogroo.ruta.Main</description>
                    <supertypeName>uima.tcas.Annotation</supertypeName>
                </typeDescription>
                <typeDescription>
                    <name>cogroo.ruta.Main.INDEFINITE</name>
                    <description>Type defined in cogroo.ruta.Main</description>
                    <supertypeName>uima.tcas.Annotation</supertypeName>
                </typeDescription>
                <typeDescription>
                    <name>cogroo.ruta.Main.CONJUNCTION</name>
                    <description>Type defined in cogroo.ruta.Main</description>
                    <supertypeName>uima.tcas.Annotation</supertypeName>
                </typeDescription>
                <typeDescription>
                    <name>cogroo.ruta.Main.SUBORDINATING_CONJUNCTION</name>
                    <description>Type defined in cogroo.ruta.Main</description>
                    <supertypeName>uima.tcas.Annotation</supertypeName>
                </typeDescription>
                <typeDescription>
                    <name>cogroo.ruta.Main.COORDINATING_CONJUNCTION</name>
                    <description>Type defined in cogroo.ruta.Main</description>
                    <supertypeName>uima.tcas.Annotation</supertypeName>
                </typeDescription>
                <typeDescription>
                    <name>cogroo.ruta.Main.INTERJECTION</name>
                    <description>Type defined in cogroo.ruta.Main</description>
                    <supertypeName>uima.tcas.Annotation</supertypeName>
                </typeDescription>
                <typeDescription>
                    <name>cogroo.ruta.Main.NOUN</name>
                    <description>Type defined in cogroo.ruta.Main</description>
                    <supertypeName>uima.tcas.Annotation</supertypeName>
                </typeDescription>
                <typeDescription>
                    <name>cogroo.ruta.Main.PROPER_NOUN</name>
                    <description>Type defined in cogroo.ruta.Main</description>
                    <supertypeName>uima.tcas.Annotation</supertypeName>
                </typeDescription>
                <typeDescription>
                    <name>cogroo.ruta.Main.NUMERAL</name>
                    <description>Type defined in cogroo.ruta.Main</description>
                    <supertypeName>uima.tcas.Annotation</supertypeName>
                </typeDescription>
                <typeDescription>
                    <name>cogroo.ruta.Main.PREPOSITION</name>
                    <description>Type defined in cogroo.ruta.Main</description>
                    <supertypeName>uima.tcas.Annotation</supertypeName>
                </typeDescription>
                <typeDescription>
                    <name>cogroo.ruta.Main.PRONOUN</name>
                    <description>Type defined in cogroo.ruta.Main</description>
                    <supertypeName>uima.tcas.Annotation</supertypeName>
                </typeDescription>
                <typeDescription>
                    <name>cogroo.ruta.Main.PERSONAL_PRONOUN</name>
                    <description>Type defined in cogroo.ruta.Main</description>
                    <supertypeName>uima.tcas.Annotation</supertypeName>
                </typeDescription>
                <typeDescription>
                    <name>cogroo.ruta.Main.DETERMINATIVE_PRONOUN</name>
                    <description>Type defined in cogroo.ruta.Main</description>
                    <supertypeName>uima.tcas.Annotation</supertypeName>
                </typeDescription>
                <typeDescription>
                    <name>cogroo.ruta.Main.INDEPENDENT_PRONOUN</name>
                    <description>Type defined in cogroo.ruta.Main</description>
                    <supertypeName>uima.tcas.Annotation</supertypeName>
                </typeDescription>
                <typeDescription>
                    <name>cogroo.ruta.Main.VERB</name>
                    <description>Type defined in cogroo.ruta.Main</description>
                    <supertypeName>uima.tcas.Annotation</supertypeName>
                </typeDescription>
                <typeDescription>
                    <name>cogroo.ruta.Main.FINITE_VERB</name>
                    <description>Type defined in cogroo.ruta.Main</description>
                    <supertypeName>uima.tcas.Annotation</supertypeName>
                </typeDescription>
                <typeDescription>
                    <name>cogroo.ruta.Main.INFINITE_VERB</name>
                    <description>Type defined in cogroo.ruta.Main</description>
                    <supertypeName>uima.tcas.Annotation</supertypeName>
                </typeDescription>
                <typeDescription>
                    <name>cogroo.ruta.Main.PARTICIPLE_VERB</name>
                    <description>Type defined in cogroo.ruta.Main</description>
                    <supertypeName>uima.tcas.Annotation</supertypeName>
                </typeDescription>
                <typeDescription>
                    <name>cogroo.ruta.Main.GERUND_VERB</name>
                    <description>Type defined in cogroo.ruta.Main</description>
                    <supertypeName>uima.tcas.Annotation</supertypeName>
                </typeDescription>
                <typeDescription>
                    <name>cogroo.ruta.Main.PRESENT</name>
                    <description>Type defined in cogroo.ruta.Main</description>
                    <supertypeName>uima.tcas.Annotation</supertypeName>
                </typeDescription>
                <typeDescription>
                    <name>cogroo.ruta.Main.IMPERFECT</name>
                    <description>Type defined in cogroo.ruta.Main</description>
                    <supertypeName>uima.tcas.Annotation</supertypeName>
                </typeDescription>
                <typeDescription>
                    <name>cogroo.ruta.Main.SIMPLE_PERFECT</name>
                    <description>Type defined in cogroo.ruta.Main</description>
                    <supertypeName>uima.tcas.Annotation</supertypeName>
                </typeDescription>
                <typeDescription>
                    <name>cogroo.ruta.Main.PLU_PERFECT</name>
                    <description>Type defined in cogroo.ruta.Main</description>
                    <supertypeName>uima.tcas.Annotation</supertypeName>
                </typeDescription>
                <typeDescription>
                    <name>cogroo.ruta.Main.FUTURE</name>
                    <description>Type defined in cogroo.ruta.Main</description>
                    <supertypeName>uima.tcas.Annotation</supertypeName>
                </typeDescription>
                <typeDescription>
                    <name>cogroo.ruta.Main.CONDITIONAL</name>
                    <description>Type defined in cogroo.ruta.Main</description>
                    <supertypeName>uima.tcas.Annotation</supertypeName>
                </typeDescription>
                <typeDescription>
                    <name>cogroo.ruta.Main.INDICATIVE</name>
                    <description>Type defined in cogroo.ruta.Main</description>
                    <supertypeName>uima.tcas.Annotation</supertypeName>
                </typeDescription>
                <typeDescription>
                    <name>cogroo.ruta.Main.SUBJUNCTIVE</name>
                    <description>Type defined in cogroo.ruta.Main</description>
                    <supertypeName>uima.tcas.Annotation</supertypeName>
                </typeDescription>
                <typeDescription>
                    <name>cogroo.ruta.Main.IMPERATIVE</name>
                    <description>Type defined in cogroo.ruta.Main</description>
                    <supertypeName>uima.tcas.Annotation</supertypeName>
                </typeDescription>
                <typeDescription>
                    <name>cogroo.ruta.Main.MALE</name>
                    <description>Type defined in cogroo.ruta.Main</description>
                    <supertypeName>uima.tcas.Annotation</supertypeName>
                </typeDescription>
                <typeDescription>
                    <name>cogroo.ruta.Main.FEMALE</name>
                    <description>Type defined in cogroo.ruta.Main</description>
                    <supertypeName>uima.tcas.Annotation</supertypeName>
                </typeDescription>
                <typeDescription>
                    <name>cogroo.ruta.Main.SINGULAR</name>
                    <description>Type defined in cogroo.ruta.Main</description>
                    <supertypeName>uima.tcas.Annotation</supertypeName>
                </typeDescription>
                <typeDescription>
                    <name>cogroo.ruta.Main.PLURAL</name>
                    <description>Type defined in cogroo.ruta.Main</description>
                    <supertypeName>uima.tcas.Annotation</supertypeName>
                </typeDescription>
                <typeDescription>
                    <name>cogroo.ruta.Main.FIRST_PERSON</name>
                    <description>Type defined in cogroo.ruta.Main</description>
                    <supertypeName>uima.tcas.Annotation</supertypeName>
                </typeDescription>
                <typeDescription>
                    <name>cogroo.ruta.Main.SECOND_PERSON</name>
                    <description>Type defined in cogroo.ruta.Main</description>
                    <supertypeName>uima.tcas.Annotation</supertypeName>
                </typeDescription>
                <typeDescription>
                    <name>cogroo.ruta.Main.THIRD_PERSON</name>
                    <description>Type defined in cogroo.ruta.Main</description>
                    <supertypeName>uima.tcas.Annotation</supertypeName>
                </typeDescription>
                <typeDescription>
                    <name>cogroo.ruta.Main.FEMALE_NOUN</name>
                    <description>Type defined in cogroo.ruta.Main</description>
                    <supertypeName>uima.tcas.Annotation</supertypeName>
                </typeDescription>
                <typeDescription>
                    <name>cogroo.ruta.Main.MALE_NOUN</name>
                    <description>Type defined in cogroo.ruta.Main</description>
                    <supertypeName>uima.tcas.Annotation</supertypeName>
                </typeDescription>
                <typeDescription>
                    <name>cogroo.ruta.Main.PLURAL_NOUN</name>
                    <description>Type defined in cogroo.ruta.Main</description>
                    <supertypeName>uima.tcas.Annotation</supertypeName>
                </typeDescription>
                <typeDescription>
                    <name>cogroo.ruta.Main.SINGULAR_NOUN</name>
                    <description>Type defined in cogroo.ruta.Main</description>
                    <supertypeName>uima.tcas.Annotation</supertypeName>
                </typeDescription>
                <typeDescription>
                    <name>cogroo.ruta.Main.PROBLEM</name>
                    <description>Type defined in cogroo.ruta.Main</description>
                    <supertypeName>uima.tcas.Annotation</supertypeName>
                </typeDescription>
                <typeDescription>
                    <name>cogroo.ruta.Main.PROBLEM_INFO</name>
                    <description>Type defined in cogroo.ruta.Main</description>
                    <supertypeName>uima.tcas.Annotation</supertypeName>
                    <features>
                        <featureDescription>
                            <name>description</name>
                            <description>description</description>
                            <rangeTypeName>uima.cas.String</rangeTypeName>
                        </featureDescription>
                        <featureDescription>
                            <name>suggestion</name>
                            <description>suggestion</description>
                            <rangeTypeName>uima.cas.String</rangeTypeName>
                        </featureDescription>
                    </features>
                </typeDescription>
                <typeDescription>
                    <name>cogroo.ruta.Main.SUGGESTION</name>
                    <description>Type defined in cogroo.ruta.Main</description>
                    <supertypeName>uima.tcas.Annotation</supertypeName>
                    <features>
                        <featureDescription>
                            <name>text</name>
                            <description>text</description>
                            <rangeTypeName>uima.cas.String</rangeTypeName>
                        </featureDescription>
                    </features>
                </typeDescription>
                <typeDescription>
                    <name>cogroo.ruta.Main.END_PRONOUN</name>
                    <description>Type defined in cogroo.ruta.Main</description>
                    <supertypeName>uima.tcas.Annotation</supertypeName>
                </typeDescription>
                <typeDescription>
                    <name>cogroo.ruta.Main.END_NOS</name>
                    <description>Type defined in cogroo.ruta.Main</description>
                    <supertypeName>uima.tcas.Annotation</supertypeName>
                </typeDescription>
                <typeDescription>
                    <name>cogroo.ruta.Main.FEMALE_ADJECTIVE</name>
                    <description>Type defined in cogroo.ruta.Main</description>
                    <supertypeName>uima.tcas.Annotation</supertypeName>
                </typeDescription>
                <typeDescription>
                    <name>cogroo.ruta.Main.MALE_ADJECTIVE</name>
                    <description>Type defined in cogroo.ruta.Main</description>
                    <supertypeName>uima.tcas.Annotation</supertypeName>
                </typeDescription>
                <typeDescription>
                    <name>cogroo.ruta.Main.PLURAL_ADJECTIVE</name>
                    <description>Type defined in cogroo.ruta.Main</description>
                    <supertypeName>uima.tcas.Annotation</supertypeName>
                </typeDescription>
                <typeDescription>
                    <name>cogroo.ruta.Main.SINGULAR_ADJECTIVE</name>
                    <description>Type defined in cogroo.ruta.Main</description>
                    <supertypeName>uima.tcas.Annotation</supertypeName>
                </typeDescription>
                <typeDescription>
                    <name>cogroo.ruta.Main.LEXEME_A</name>
                    <description>Type defined in cogroo.ruta.Main</description>
                    <supertypeName>uima.tcas.Annotation</supertypeName>
                </typeDescription>
                <typeDescription>
                    <name>cogroo.ruta.Main.LEXEME_AS</name>
                    <description>Type defined in cogroo.ruta.Main</description>
                    <supertypeName>uima.tcas.Annotation</supertypeName>
                </typeDescription>
                <typeDescription>
                    <name>cogroo.ruta.Main.LEXEME_A_OR_AS</name>
                    <description>Type defined in cogroo.ruta.Main</description>
                    <supertypeName>uima.tcas.Annotation</supertypeName>
                </typeDescription>
                <typeDescription>
                    <name>cogroo.ruta.Main.PREPOSITION_A</name>
                    <description>Type defined in cogroo.ruta.Main</description>
                    <supertypeName>uima.tcas.Annotation</supertypeName>
                </typeDescription>
                <typeDescription>
                    <name>cogroo.ruta.Main.ARTICLE_A</name>
                    <description>Type defined in cogroo.ruta.Main</description>
                    <supertypeName>uima.tcas.Annotation</supertypeName>
                </typeDescription>
                <typeDescription>
                    <name>cogroo.ruta.Main.CRASE</name>
                    <description>Type defined in cogroo.ruta.Main</description>
                    <supertypeName>uima.tcas.Annotation</supertypeName>
                </typeDescription>
                <typeDescription>
                    <name>cogroo.ruta.Main.CRASE_A</name>
                    <description>Type defined in cogroo.ruta.Main</description>
                    <supertypeName>uima.tcas.Annotation</supertypeName>
                </typeDescription>
                <typeDescription>
                    <name>cogroo.ruta.Main.CRASE_AS</name>
                    <description>Type defined in cogroo.ruta.Main</description>
                    <supertypeName>uima.tcas.Annotation</supertypeName>
                </typeDescription>
                <typeDescription>
                    <name>cogroo.ruta.Main.PRON_TRATAMENTO</name>
                    <description>Type defined in cogroo.ruta.Main</description>
                    <supertypeName>uima.tcas.Annotation</supertypeName>
                </typeDescription>
                <typeDescription>
                    <name>cogroo.ruta.Main.EM_RELACAO</name>
                    <description>Type defined in cogroo.ruta.Main</description>
                    <supertypeName>uima.tcas.Annotation</supertypeName>
                </typeDescription>
                <typeDescription>
                    <name>cogroo.ruta.Main.COM_RELACAO</name>
                    <description>Type defined in cogroo.ruta.Main</description>
                    <supertypeName>uima.tcas.Annotation</supertypeName>
                </typeDescription>
                <typeDescription>
                    <name>cogroo.ruta.Main.FAZER_TEMPO</name>
                    <description>Type defined in cogroo.ruta.Main</description>
                    <supertypeName>uima.tcas.Annotation</supertypeName>
                </typeDescription>
                <typeDescription>
                    <name>cogroo.ruta.Main.EXP_TEMPO_S</name>
                    <description>Type defined in cogroo.ruta.Main</description>
                    <supertypeName>uima.tcas.Annotation</supertypeName>
                </typeDescription>
                <typeDescription>
                    <name>cogroo.ruta.Main.EXP_TEMPO_P</name>
                    <description>Type defined in cogroo.ruta.Main</description>
                    <supertypeName>uima.tcas.Annotation</supertypeName>
                </typeDescription>
                <typeDescription>
                    <name>cogroo.ruta.Main.VERB_LIST</name>
                    <description>Type defined in cogroo.ruta.Main</description>
                    <supertypeName>uima.tcas.Annotation</supertypeName>
                </typeDescription>
                <typeDescription>
                    <name>cogroo.ruta.Main.SE_OU_QUANDO</name>
                    <description>Type defined in cogroo.ruta.Main</description>
                    <supertypeName>uima.tcas.Annotation</supertypeName>
                </typeDescription>
                <typeDescription>
                    <name>cogroo.ruta.Main.EU_OU_ELE</name>
                    <description>Type defined in cogroo.ruta.Main</description>
                    <supertypeName>uima.tcas.Annotation</supertypeName>
                </typeDescription>
                <typeDescription>
                    <name>cogroo.ruta.Main.VERB_IRREG_75_77</name>
                    <description>Type defined in cogroo.ruta.Main</description>
                    <supertypeName>uima.tcas.Annotation</supertypeName>
                </typeDescription>
                <typeDescription>
                    <name>cogroo.ruta.Main.MAL</name>
                    <description>Type defined in cogroo.ruta.Main</description>
                    <supertypeName>uima.tcas.Annotation</supertypeName>
                </typeDescription>
                <typeDescription>
                    <name>cogroo.ruta.Main.MAU</name>
                    <description>Type defined in cogroo.ruta.Main</description>
                    <supertypeName>uima.tcas.Annotation</supertypeName>
                </typeDescription>
                <typeDescription>
                    <name>cogroo.ruta.Main.MEIA_SUB</name>
                    <description>Type defined in cogroo.ruta.Main</description>
                    <supertypeName>uima.tcas.Annotation</supertypeName>
                </typeDescription>
                <typeDescription>
                    <name>cogroo.ruta.Main.MEIA_NUM</name>
                    <description>Type defined in cogroo.ruta.Main</description>
                    <supertypeName>uima.tcas.Annotation</supertypeName>
                </typeDescription>
                <typeDescription>
                    <name>cogroo.ruta.Main.LEXEME_DE</name>
                    <description>Type defined in cogroo.ruta.Main</description>
                    <supertypeName>uima.tcas.Annotation</supertypeName>
                </typeDescription>
                <typeDescription>
                    <name>cogroo.ruta.Main.LEXEME_O</name>
                    <description>Type defined in cogroo.ruta.Main</description>
                    <supertypeName>uima.tcas.Annotation</supertypeName>
                </typeDescription>
                <typeDescription>
                    <name>cogroo.ruta.Main.LEXEME_DO</name>
                    <description>Type defined in cogroo.ruta.Main</description>
                    <supertypeName>uima.tcas.Annotation</supertypeName>
                </typeDescription>
            </types>
        </typeSystemDescription>
        <typePriorities>
            <priorityList>
                <type>org.apache.uima.ruta.type.RutaFrame</type>
                <type>uima.tcas.Annotation</type>
                <type>org.apache.uima.ruta.type.RutaBasic</type>
            </priorityList>
        </typePriorities>
        <fsIndexCollection/>
        <capabilities>
            <capability>
                <inputs/>
                <outputs/>
                <languagesSupported/>
            </capability>
            <capability>
                <inputs>
                    <type>cogroo.ruta.Main.ADJECTIVE</type>
                    <type>cogroo.ruta.Main.ADVERB</type>
                    <type>cogroo.ruta.Main.ARTICLE</type>
                    <type>cogroo.ruta.Main.DEFINITE</type>
                    <type>cogroo.ruta.Main.INDEFINITE</type>
                    <type>cogroo.ruta.Main.CONJUNCTION</type>
                    <type>cogroo.ruta.Main.SUBORDINATING_CONJUNCTION</type>
                    <type>cogroo.ruta.Main.COORDINATING_CONJUNCTION</type>
                    <type>cogroo.ruta.Main.INTERJECTION</type>
                    <type>cogroo.ruta.Main.NOUN</type>
                    <type>cogroo.ruta.Main.PROPER_NOUN</type>
                    <type>cogroo.ruta.Main.NUMERAL</type>
                    <type>cogroo.ruta.Main.PREPOSITION</type>
                    <type>cogroo.ruta.Main.PRONOUN</type>
                    <type>cogroo.ruta.Main.PERSONAL_PRONOUN</type>
                    <type>cogroo.ruta.Main.DETERMINATIVE_PRONOUN</type>
                    <type>cogroo.ruta.Main.INDEPENDENT_PRONOUN</type>
                    <type>cogroo.ruta.Main.VERB</type>
                    <type>cogroo.ruta.Main.FINITE_VERB</type>
                    <type>cogroo.ruta.Main.INFINITE_VERB</type>
                    <type>cogroo.ruta.Main.PARTICIPLE_VERB</type>
                    <type>cogroo.ruta.Main.GERUND_VERB</type>
                    <type>cogroo.ruta.Main.PRESENT</type>
                    <type>cogroo.ruta.Main.IMPERFECT</type>
                    <type>cogroo.ruta.Main.SIMPLE_PERFECT</type>
                    <type>cogroo.ruta.Main.PLU_PERFECT</type>
                    <type>cogroo.ruta.Main.FUTURE</type>
                    <type>cogroo.ruta.Main.CONDITIONAL</type>
                    <type>cogroo.ruta.Main.INDICATIVE</type>
                    <type>cogroo.ruta.Main.SUBJUNCTIVE</type>
                    <type>cogroo.ruta.Main.IMPERATIVE</type>
                    <type>cogroo.ruta.Main.MALE</type>
                    <type>cogroo.ruta.Main.FEMALE</type>
                    <type>cogroo.ruta.Main.SINGULAR</type>
                    <type>cogroo.ruta.Main.PLURAL</type>
                    <type>cogroo.ruta.Main.FIRST_PERSON</type>
                    <type>cogroo.ruta.Main.SECOND_PERSON</type>
                    <type>cogroo.ruta.Main.THIRD_PERSON</type>
                    <type>cogroo.ruta.Main.FEMALE_NOUN</type>
                    <type>cogroo.ruta.Main.MALE_NOUN</type>
                    <type>cogroo.ruta.Main.PLURAL_NOUN</type>
                    <type>cogroo.ruta.Main.SINGULAR_NOUN</type>
                    <type>cogroo.ruta.Main.PROBLEM</type>
                    <type>cogroo.ruta.Main.PROBLEM_INFO</type>
                    <type>cogroo.ruta.Main.SUGGESTION</type>
                    <type>cogroo.ruta.Main.END_PRONOUN</type>
                    <type>cogroo.ruta.Main.END_NOS</type>
                    <type>cogroo.ruta.Main.FEMALE_ADJECTIVE</type>
                    <type>cogroo.ruta.Main.MALE_ADJECTIVE</type>
                    <type>cogroo.ruta.Main.PLURAL_ADJECTIVE</type>
                    <type>cogroo.ruta.Main.SINGULAR_ADJECTIVE</type>
                    <type>cogroo.ruta.Main.LEXEME_A</type>
                    <type>cogroo.ruta.Main.LEXEME_AS</type>
                    <type>cogroo.ruta.Main.LEXEME_A_OR_AS</type>
                    <type>cogroo.ruta.Main.PREPOSITION_A</type>
                    <type>cogroo.ruta.Main.ARTICLE_A</type>
                    <type>cogroo.ruta.Main.CRASE</type>
                    <type>cogroo.ruta.Main.CRASE_A</type>
                    <type>cogroo.ruta.Main.CRASE_AS</type>
                    <type>cogroo.ruta.Main.PRON_TRATAMENTO</type>
                    <type>cogroo.ruta.Main.EM_RELACAO</type>
                    <type>cogroo.ruta.Main.COM_RELACAO</type>
                    <type>cogroo.ruta.Main.FAZER_TEMPO</type>
                    <type>cogroo.ruta.Main.EXP_TEMPO_S</type>
                    <type>cogroo.ruta.Main.EXP_TEMPO_P</type>
                    <type>cogroo.ruta.Main.VERB_LIST</type>
                    <type>cogroo.ruta.Main.SE_OU_QUANDO</type>
                    <type>cogroo.ruta.Main.EU_OU_ELE</type>
                    <type>cogroo.ruta.Main.VERB_IRREG_75_77</type>
                    <type>cogroo.ruta.Main.MAL</type>
                    <type>cogroo.ruta.Main.MAU</type>
                    <type>cogroo.ruta.Main.MEIA_SUB</type>
                    <type>cogroo.ruta.Main.MEIA_NUM</type>
                    <type>cogroo.ruta.Main.LEXEME_DE</type>
                    <type>cogroo.ruta.Main.LEXEME_O</type>
                    <type>cogroo.ruta.Main.LEXEME_DO</type>
                </inputs>
                <outputs>
                    <type>cogroo.ruta.Main.ADJECTIVE</type>
                    <type>cogroo.ruta.Main.ADVERB</type>
                    <type>cogroo.ruta.Main.ARTICLE</type>
                    <type>cogroo.ruta.Main.DEFINITE</type>
                    <type>cogroo.ruta.Main.INDEFINITE</type>
                    <type>cogroo.ruta.Main.CONJUNCTION</type>
                    <type>cogroo.ruta.Main.SUBORDINATING_CONJUNCTION</type>
                    <type>cogroo.ruta.Main.COORDINATING_CONJUNCTION</type>
                    <type>cogroo.ruta.Main.INTERJECTION</type>
                    <type>cogroo.ruta.Main.NOUN</type>
                    <type>cogroo.ruta.Main.PROPER_NOUN</type>
                    <type>cogroo.ruta.Main.NUMERAL</type>
                    <type>cogroo.ruta.Main.PREPOSITION</type>
                    <type>cogroo.ruta.Main.PRONOUN</type>
                    <type>cogroo.ruta.Main.PERSONAL_PRONOUN</type>
                    <type>cogroo.ruta.Main.DETERMINATIVE_PRONOUN</type>
                    <type>cogroo.ruta.Main.INDEPENDENT_PRONOUN</type>
                    <type>cogroo.ruta.Main.VERB</type>
                    <type>cogroo.ruta.Main.FINITE_VERB</type>
                    <type>cogroo.ruta.Main.INFINITE_VERB</type>
                    <type>cogroo.ruta.Main.PARTICIPLE_VERB</type>
                    <type>cogroo.ruta.Main.GERUND_VERB</type>
                    <type>cogroo.ruta.Main.PRESENT</type>
                    <type>cogroo.ruta.Main.IMPERFECT</type>
                    <type>cogroo.ruta.Main.SIMPLE_PERFECT</type>
                    <type>cogroo.ruta.Main.PLU_PERFECT</type>
                    <type>cogroo.ruta.Main.FUTURE</type>
                    <type>cogroo.ruta.Main.CONDITIONAL</type>
                    <type>cogroo.ruta.Main.INDICATIVE</type>
                    <type>cogroo.ruta.Main.SUBJUNCTIVE</type>
                    <type>cogroo.ruta.Main.IMPERATIVE</type>
                    <type>cogroo.ruta.Main.MALE</type>
                    <type>cogroo.ruta.Main.FEMALE</type>
                    <type>cogroo.ruta.Main.SINGULAR</type>
                    <type>cogroo.ruta.Main.PLURAL</type>
                    <type>cogroo.ruta.Main.FIRST_PERSON</type>
                    <type>cogroo.ruta.Main.SECOND_PERSON</type>
                    <type>cogroo.ruta.Main.THIRD_PERSON</type>
                    <type>cogroo.ruta.Main.FEMALE_NOUN</type>
                    <type>cogroo.ruta.Main.MALE_NOUN</type>
                    <type>cogroo.ruta.Main.PLURAL_NOUN</type>
                    <type>cogroo.ruta.Main.SINGULAR_NOUN</type>
                    <type>cogroo.ruta.Main.PROBLEM</type>
                    <type>cogroo.ruta.Main.PROBLEM_INFO</type>
                    <type>cogroo.ruta.Main.SUGGESTION</type>
                    <type>cogroo.ruta.Main.END_PRONOUN</type>
                    <type>cogroo.ruta.Main.END_NOS</type>
                    <type>cogroo.ruta.Main.FEMALE_ADJECTIVE</type>
                    <type>cogroo.ruta.Main.MALE_ADJECTIVE</type>
                    <type>cogroo.ruta.Main.PLURAL_ADJECTIVE</type>
                    <type>cogroo.ruta.Main.SINGULAR_ADJECTIVE</type>
                    <type>cogroo.ruta.Main.LEXEME_A</type>
                    <type>cogroo.ruta.Main.LEXEME_AS</type>
                    <type>cogroo.ruta.Main.LEXEME_A_OR_AS</type>
                    <type>cogroo.ruta.Main.PREPOSITION_A</type>
                    <type>cogroo.ruta.Main.ARTICLE_A</type>
                    <type>cogroo.ruta.Main.CRASE</type>
                    <type>cogroo.ruta.Main.CRASE_A</type>
                    <type>cogroo.ruta.Main.CRASE_AS</type>
                    <type>cogroo.ruta.Main.PRON_TRATAMENTO</type>
                    <type>cogroo.ruta.Main.EM_RELACAO</type>
                    <type>cogroo.ruta.Main.COM_RELACAO</type>
                    <type>cogroo.ruta.Main.FAZER_TEMPO</type>
                    <type>cogroo.ruta.Main.EXP_TEMPO_S</type>
                    <type>cogroo.ruta.Main.EXP_TEMPO_P</type>
                    <type>cogroo.ruta.Main.VERB_LIST</type>
                    <type>cogroo.ruta.Main.SE_OU_QUANDO</type>
                    <type>cogroo.ruta.Main.EU_OU_ELE</type>
                    <type>cogroo.ruta.Main.VERB_IRREG_75_77</type>
                    <type>cogroo.ruta.Main.MAL</type>
                    <type>cogroo.ruta.Main.MAU</type>
                    <type>cogroo.ruta.Main.MEIA_SUB</type>
                    <type>cogroo.ruta.Main.MEIA_NUM</type>
                    <type>cogroo.ruta.Main.LEXEME_DE</type>
                    <type>cogroo.ruta.Main.LEXEME_O</type>
                    <type>cogroo.ruta.Main.LEXEME_DO</type>
                </outputs>
                <languagesSupported/>
            </capability>
        </capabilities>
        <operationalProperties>
            <modifiesCas>true</modifiesCas>
            <multipleDeploymentAllowed>true</multipleDeploymentAllowed>
            <outputsNewCASes>true</outputsNewCASes>
        </operationalProperties>
    </analysisEngineMetaData>
    <resourceManagerConfiguration/>
</analysisEngineDescription>
